{
  "format_version" : "1.20.20",

  "sound_definitions" : {
    "entity.generic.splash" : {
      "__use_legacy_max_distance" : "true",
      "category" : "player",
      "max_distance" : null,
      "min_distance" : null,
      "sounds" : [
         {
            "load_on_low_memory" : true,
            "name" : "sounds/random/splash"
         }
      ]
    },
    
    "random.splash" : {
       "__use_legacy_max_distance" : "true",
       "category" : "player",
       "max_distance" : null,
       "min_distance" : null,
       "sounds" : [
          {
             "load_on_low_memory" : true,
             "name" : "sounds/random/splash"
          }
       ]
    },
    
    "ambient.underwater.enter": {
      "sounds": []
    },
  
    "ambient.underwater.exit": {
      "sounds": []
    }
  }
}